consulta_correios/__init__.py
consulta_correios/correios_api.py
Consulta_Correios-1.0.1.dist-info/LICENSE
Consulta_Correios-1.0.1.dist-info/METADATA
Consulta_Correios-1.0.1.dist-info/WHEEL
Consulta_Correios-1.0.1.dist-info/top_level.txt
Consulta_Correios-1.0.1.dist-info/RECORD
