Metadata-Version: 2.1
Name: Consulta-Correios
Version: 1.0.1
Summary: API para consulta de endereços e CEPs  utilizando o site dos Correios
Home-page: https://github.com/arthurfortes/consulta_correios
Author: Arthur Fortes
Author-email: fortes.arthur@gmail.com
License: UNKNOWN
Keywords: python endereco cep correios busca
Platform: UNKNOWN
Classifier: Programming Language :: Python :: 3
Classifier: License :: OSI Approved :: MIT License
Classifier: Operating System :: OS Independent
Classifier: Natural Language :: Portuguese
Classifier: Intended Audience :: Developers
